api4all/__init__.py
api4all/base.py
api4all/keys.py
api4all/data/__init__.py
api4all/data/constant_data.py
api4all/data/data.py
api4all/engines/__init__.py
api4all/engines/engines.py
api4all/engines/factory.py
api4all/examples/quick-start-with-env-file.py
api4all/examples/quick-start.py
api4all/logger/__init__.py
api4all/logger/base_logger.py
api4all/utils/__init__.py
api4all/utils/configs.py
api4all/utils/models.py
api4all/utils/utils.py
api4all-0.4.0.dist-info/LICENSE
api4all-0.4.0.dist-info/METADATA
api4all-0.4.0.dist-info/WHEEL
api4all-0.4.0.dist-info/top_level.txt
api4all-0.4.0.dist-info/RECORD
