Metadata-Version: 2.1
Name: api4all
Version: 0.4.0
Summary: Easy-to-use LLM API from a state-of-the-art provider and comparison
Author-email: Hieu Nguyen <hieung.tech@gmail.com>
Maintainer-email: Hieu Nguyen <hieung.tech@gmail.com>
License: MIT License
Project-URL: Homepage, https://github.com/hieuminh65/api4all
Project-URL: Documentation, https://github.com/hieuminh65/api4all
Project-URL: Repository, https://github.com/hieuminh65/api4all
Project-URL: Changelog, https://github.com/hieuminh65/api4all/blob/main/CHANGELOG.md
Keywords: llm,llmapi,llminference,llmprovider,llmprice,llmlearderboard,llmpricing
Classifier: Programming Language :: Python :: 3
Classifier: License :: OSI Approved :: MIT License
Classifier: Operating System :: OS Independent
Requires-Python: >=3.8
License-File: LICENSE
Requires-Dist: openai ==1.13.3
Requires-Dist: anthropic ==0.19.1
Requires-Dist: fireworks-ai ==0.13.0
Requires-Dist: groq ==0.4.2
Requires-Dist: mistralai ==0.1.6
Requires-Dist: python-dotenv ==1.0.1
Requires-Dist: replicate ==0.24.0
Requires-Dist: together ==0.2.11
Requires-Dist: google-generativeai ==0.4.1
